_faststat.so
faststat/__init__.py
faststat/cache.py
faststat/faststat.py
faststat/format.py
faststat/test.py
faststat-17.10.0.dist-info/DESCRIPTION.rst
faststat-17.10.0.dist-info/METADATA
faststat-17.10.0.dist-info/RECORD
faststat-17.10.0.dist-info/WHEEL
faststat-17.10.0.dist-info/metadata.json
faststat-17.10.0.dist-info/top_level.txt
