Metadata-Version: 2.0
Name: faststat
Version: 17.10.0
Summary: fast online statistics collection
Home-page: http://github.com/doublereedkurt/faststat
Author: Kurt Rose
Author-email: kurt@kurtrose.com
License: MIT
Platform: UNKNOWN
Classifier: Development Status :: 4 - Beta
Classifier: License :: OSI Approved :: MIT License
